build/lib/build/lib/scripts/ingest_manage_csv.py
build/lib/build/lib/seals/__init__.py
build/lib/build/lib/seals/compile_cython_functions.py
build/lib/build/lib/seals/config.py
build/lib/build/lib/seals/run_seals_custom_coarse_algorithm.py
build/lib/build/lib/seals/run_seals_standard.py
build/lib/build/lib/seals/run_seals_standard_fast.py
build/lib/build/lib/seals/seals_api_parsing.py
build/lib/build/lib/seals/seals_generate_base_data.py
build/lib/build/lib/seals/seals_initialize_project.py
build/lib/build/lib/seals/seals_main.py
build/lib/build/lib/seals/seals_process_coarse_timeseries.py
build/lib/build/lib/seals/seals_tasks.py
build/lib/build/lib/seals/seals_utils.py
build/lib/build/lib/seals/seals_visualization_functions.py
build/lib/build/lib/seals/seals_visualization_tasks.py
build/lib/build/lib/seals/old_run_files/run_global_ssps.py
build/lib/build/lib/seals/old_run_files/run_t_all_supported_allocations.py
build/lib/build/lib/seals/old_run_files/run_t_multiple.py
build/lib/build/lib/seals/old_run_files/run_t_vector_aoi.py
build/lib/scripts/ingest_manage_csv.py
build/lib/seals/__init__.py
build/lib/seals/compile_cython_functions.py
build/lib/seals/config.py
build/lib/seals/run_seals_custom_coarse_algorithm.py
build/lib/seals/run_seals_standard.py
build/lib/seals/run_seals_standard_fast.py
build/lib/seals/seals_api_parsing.py
build/lib/seals/seals_generate_base_data.py
build/lib/seals/seals_initialize_project.py
build/lib/seals/seals_main.py
build/lib/seals/seals_process_coarse_timeseries.py
build/lib/seals/seals_tasks.py
build/lib/seals/seals_utils.py
build/lib/seals/seals_visualization_functions.py
build/lib/seals/seals_visualization_tasks.py
build/lib/seals/old_run_files/run_global_ssps.py
build/lib/seals/old_run_files/run_t_all_supported_allocations.py
build/lib/seals/old_run_files/run_t_multiple.py
build/lib/seals/old_run_files/run_t_vector_aoi.py
scripts/ingest_manage_csv.py
seals/__init__.py
seals/compile_cython_functions.py
seals/config.py
sealsmodel-1.1.0.dist-info/LICENSE
sealsmodel-1.1.0.dist-info/METADATA
sealsmodel-1.1.0.dist-info/WHEEL
sealsmodel-1.1.0.dist-info/top_level.txt
sealsmodel-1.1.0.dist-info/RECORD
