Metadata-Version: 2.1
Name: sealsmodel
Version: 1.1.0
Summary: Land-use change model and downscaler
Maintainer: Justin Andrew Johnson
License: Creative Commons Attribution-NonCommercial-ShareAlike 4.0 International Public License with Contributor License Agreement
Project-URL: repository, https://github.com/jandrewjohnson/seals_dev
Keywords: geospatial,raster,shapefile
Classifier: Development Status :: 5 - Production/Stable
Classifier: Intended Audience :: Science/Research
Classifier: Programming Language :: Cython
Classifier: Programming Language :: Python :: 3
Requires-Python: >=3.6
License-File: LICENSE
